beancount_multitool/ChaseSPCard.py
beancount_multitool/Institution.py
beancount_multitool/JABank.py
beancount_multitool/MappingDatabase.py
beancount_multitool/RakutenBank.py
beancount_multitool/RakutenCard.py
beancount_multitool/ShinseiBank.py
beancount_multitool/SumishinNetBank.py
beancount_multitool/__init__.py
beancount_multitool/__main__.py
beancount_multitool/__version__.py
beancount_multitool/as_transaction.py
beancount_multitool/cli.py
beancount_multitool/get_beancount_config.py
beancount_multitool/get_value.py
beancount_multitool/read_config.py
beancount_multitool/tests/test_get_beancount_config.py
beancount_multitool/tests/test_get_value.py
beancount_multitool/tests/test_read_config.py
beancount_multitool-0.7.1.dist-info/LICENSE
beancount_multitool-0.7.1.dist-info/METADATA
beancount_multitool-0.7.1.dist-info/WHEEL
beancount_multitool-0.7.1.dist-info/entry_points.txt
beancount_multitool-0.7.1.dist-info/RECORD
