Metadata-Version: 2.3
Name: beancount-multitool
Version: 0.7.1
Summary: A CLI tool that converts financial data to Beancount files
License: MIT
Author: Rick Lan
Author-email: rlan@users.noreply.github.com
Requires-Python: >=3.9
Classifier: Development Status :: 4 - Beta
Classifier: Framework :: Pytest
Classifier: Intended Audience :: Financial and Insurance Industry
Classifier: License :: OSI Approved :: MIT License
Classifier: Natural Language :: English
Classifier: Natural Language :: Japanese
Classifier: Operating System :: OS Independent
Classifier: Programming Language :: Python :: 3
Classifier: Programming Language :: Python :: 3.9
Classifier: Programming Language :: Python :: 3.10
Classifier: Programming Language :: Python :: 3.11
Classifier: Programming Language :: Python :: 3.12
Classifier: Programming Language :: Python :: 3.13
Classifier: Topic :: Office/Business :: Financial :: Accounting
Classifier: Topic :: Office/Business :: Financial :: Investment
Classifier: Topic :: Text Processing :: General
Classifier: Topic :: Utilities
Requires-Dist: click (>=8.1.7)
Requires-Dist: pandas (>=2.2.2)
Requires-Dist: tqdm (>=4.66.4)
Project-URL: Bug Tracker, https://github.com/rlan/beancount-multitool/issues
Project-URL: Documentation, https://rlan.github.io/beancount-multitool/
Project-URL: Homepage, https://github.com/rlan/beancount-multitool
Project-URL: Repository, https://github.com/rlan/beancount-multitool
